Metadata-Version: 2.1
Name: edgerun-galileo
Version: 0.8.0
Summary: Galileo: A framework for distributed load testing experiments
Home-page: https://github.com/edgerun/galileo
Author: Thomas Rausch
Author-email: t.rausch@dsg.tuwien.ac.at
License: UNKNOWN
Platform: UNKNOWN
Classifier: Programming Language :: Python :: 3
Classifier: Operating System :: OS Independent
